pygics/__init__.py
pygics/common.py
pygics/constant.py
pygics/plugin.py
pygics/sdk.py
pygics/service.py
pygics/struct.py
pygics/task.py
pygics/static/favicon.ico
pygics/static/pygics.css
pygics/static/pygics.js
pygics-1.1.4.dist-info/LICENSE.txt
pygics-1.1.4.dist-info/METADATA
pygics-1.1.4.dist-info/WHEEL
pygics-1.1.4.dist-info/top_level.txt
pygics-1.1.4.dist-info/RECORD
