Metadata-Version: 2.1
Name: pygics
Version: 1.1.4
Summary: Python Gevent Interface for Communication Service
Home-page: https://github.com/HyechurnJang/pygics
Author: Hyechurn Jang
Author-email: jangh@vmware.com
License: Apache 2.0
Platform: UNKNOWN
Classifier: License :: OSI Approved :: Apache Software License
Classifier: Topic :: Software Development :: Libraries :: Python Modules
Classifier: Programming Language :: Python :: 3
Requires-Dist: gevent
Requires-Dist: requests
Requires-Dist: PyYAML
Requires-Dist: watchdog
Requires-Dist: watchdog-gevent
Requires-Dist: SQLAlchemy
